Seq_det/seq_111.v
module seq_111(x, clk, reset, out);
    input x, clk, reset;
    output out;
    wire Q1, Q0;
    wire J1, K1, J0, K0;

    // Excitation equations from K-map
    assign J1 = x & Q0;
    assign K1 = (~x) & Q0;
    assign J0 = x & ~Q1 & ~Q0;
    assign K0 = (~x) | Q1;

    // Instantiate JK flip-flops
    jkff FF1(J1, K1, clk, reset, Q1);
    jkff FF0(J0, K0, clk, reset, Q0);

    // Output logic
    assign out = Q1 & Q0 & x;
endmodule


module jkff(J, K, clk, reset, Q);
    input J, K, clk, reset;
    output reg Q;

    always @(posedge clk or posedge reset) begin
        if (reset)
            Q <= 0;
        else
            case ({J,K})
                2'b00: Q <= Q;      // No change
                2'b01: Q <= 0;      // Reset
                2'b10: Q <= 1;      // Set
                2'b11: Q <= ~Q;     // Toggle
            endcase
    end
endmodule


// Testbench
module seq_111_tb();
    reg x, clk, reset;
    wire out;

    seq_111 DUT(x, clk, reset, out);

    initial clk = 0;
    always #5 clk = ~clk;

    initial begin
        $display("Time\tclk\tx\tout");
        $monitor("%0d\t%b\t%b\t%b", $time, clk, x, out);

        reset = 1; x = 0;
        #6 reset = 0;

        // Input stream to test overlap
        #4 x=1;
        #10 x=1;
        #10 x=1;  // detect here
        #10 x=1;  // overlap detect again
        #10 x=0;
        #10 x=1;
        #10 x=1;
        #10 x=1;  // detect here
        #10 x=0;
        #10 $finish;
    end

    initial begin
        $dumpfile("seq_111.vcd");
        $dumpvars;
    end
endmodule

Seq_det/seq_111.vcd
$date
	Sat Aug 30 19:27:57 2025
$end
$version
	Icarus Verilog
$end
$timescale
	1s
$end
$scope module seq_111_tb $end
$var wire 1 ! out $end
$var reg 1 " clk $end
$var reg 1 # reset $end
$var reg 1 $ x $end
$scope module DUT $end
$var wire 1 % J0 $end
$var wire 1 & J1 $end
$var wire 1 ' K0 $end
$var wire 1 ( K1 $end
$var wire 1 " clk $end
$var wire 1 ! out $end
$var wire 1 # reset $end
$var wire 1 $ x $end
$var wire 1 ) Q1 $end
$var wire 1 * Q0 $end
$scope module FF0 $end
$var wire 1 % J $end
$var wire 1 ' K $end
$var wire 1 " clk $end
$var wire 1 # reset $end
$var reg 1 * Q $end
$upscope $end
$scope module FF1 $end
$var wire 1 & J $end
$var wire 1 ( K $end
$var wire 1 " clk $end
$var wire 1 # reset $end
$var reg 1 ) Q $end
$upscope $end
$upscope $end
$upscope $end
$enddefinitions $end
$comment Show the parameter values. $end
$dumpall
$end
#0
$dumpvars
0*
0)
0(
1'
0&
0%
0$
1#
0"
0!
$end
#5
1"
#6
0#
#10
1%
0'
1$
0"
#15
0%
1&
1*
1"
#20
0"
#25
1!
1'
1)
1"
#30
0"
#35
0!
0&
0*
1"
#40
0"
#45
1"
#50
0"
0$
#55
1"
#60
0"
1$
#65
1"
#70
0"
#75
1"
#80
0"
#85
1"
#90
0"
0$
