Seq_det/Seq_det.v
module seq_det(clk,x,z);
input clk,x;
output reg z;
reg [1:0] state;
parameter s0=0,s1=1,s2=2,s3=3;
always@(posedge clk)
case(state)
s0:z<=0;
s1:z<=0;
s2:z<=0;
s3:z<=x?0:1;
default: z<=0;
endcase
always@(posedge clk)
case(state)
s0:state<=x?s0:s1;
s1:state<=x?s2:s1;
s2:state<=x?s3:s1;
s3:state<=x?s0:s1;
default: state<=s0;
endcase
endmodule
//Testbench
`timescale 1ns/1ps
module seq_det_tb;
reg clk,x;
wire z;
integer i;
seq_det DUT(clk,x,z);
initial clk=0;
always #5 clk=~clk;
always @(posedge clk) begin
$monitor("%dns\t%b\t%b\t%b",$time,clk,x,z);
end
initial 
begin
    $dumpfile("Seq_det.vcd");
$dumpvars(0,seq_det_tb);
$display("Time\tclock\tinput\toutput");
$monitor("%dns\t%b\t%b\t%b",$time,clk,x,z);
end
initial begin
   #2;
   for (i=0; i<10; i++)
    begin
        if (i%2==0) 
        begin
        x=0;
        #20; 
        end
        else 
        begin
        x=1;
        #20;
         end
    end
#200 $finish;
end
endmodule

Seq_det/Seq_det.vcd
$date
	Sat Jun 21 11:04:16 2025
$end
$version
	Icarus Verilog
$end
$timescale
	1ps
$end
$scope module seq_det_tb $end
$var wire 1 ! z $end
$var reg 1 " clk $end
$var reg 1 # x $end
$var integer 32 $ i [31:0] $end
$scope module DUT $end
$var wire 1 " clk $end
$var wire 1 # x $end
$var parameter 32 % s0 $end
$var parameter 32 & s1 $end
$var parameter 32 ' s2 $end
$var parameter 32 ( s3 $end
$var reg 2 ) state [1:0] $end
$var reg 1 ! z $end
$upscope $end
$upscope $end
$enddefinitions $end
$comment Show the parameter values. $end
$dumpall
b11 (
b10 '
b1 &
b0 %
$end
#0
$dumpvars
bx )
bx $
x#
0"
x!
$end
#2000
0#
b0 $
#5000
0!
b0 )
1"
#10000
0"
#15000
b1 )
1"
#20000
0"
#22000
1#
b1 $
#25000
b10 )
1"
#30000
0"
#35000
b11 )
1"
#40000
0"
#42000
0#
b10 $
#45000
1!
b1 )
1"
#50000
0"
#55000
0!
1"
#60000
0"
#62000
1#
b11 $
#65000
b10 )
1"
#70000
0"
#75000
b11 )
1"
#80000
0"
#82000
0#
b100 $
#85000
1!
b1 )
1"
#90000
0"
#95000
0!
1"
#100000
0"
#102000
1#
b101 $
#105000
b10 )
1"
#110000
0"
#115000
b11 )
1"
#120000
0"
#122000
0#
b110 $
#125000
1!
b1 )
1"
#130000
0"
#135000
0!
1"
#140000
0"
#142000
1#
b111 $
#145000
b10 )
1"
#150000
0"
#155000
b11 )
1"
#160000
0"
#162000
0#
b1000 $
#165000
1!
b1 )
1"
#170000
0"
#175000
0!
1"
#180000
0"
#182000
1#
b1001 $
#185000
b10 )
1"
#190000
0"
#195000
b11 )
1"
#200000
0"
#202000
b1010 $
#205000
b0 )
1"
