Counters/four_bit_ripple_counter.v
module four_bit_RC(t,clk,rst,q);
input clk;
input rst;
input [3:0] t;
output wire [3:0] q;
tff M1(.in(t[0]),.clk(clk),.rst(rst),.out(q[0]));
tff M2(.in(t[1]),.clk(q[0]),.rst(rst),.out(q[1]));
tff M3(.in(t[2]),.clk(q[1]),.rst(rst),.out(q[2]));
tff M4(.in(t[3]),.clk(q[2]),.rst(rst),.out(q[3]));
endmodule
module tff(in,clk,rst,out);
input in,clk,rst;
output reg out;
always @(posedge clk, rst) begin
    if (rst)
    out<=0;
    else begin
if (in)
out<=~out;
else
out<=out;
    end
end
endmodule
//Test bench
module four_bit_RC_tb;
reg clk;
reg rst;
reg [3:0] t;
wire [3:0] q;
four_bit_RC DUT(t,clk,rst,q);
initial clk=0;
always #5 clk=~clk;
initial begin
    $display("Time\tClock\tState");
    $monitor("%d\t%b\t%b",$time,clk,q);
    t=4'b1111;
    rst=1;
    #7 rst=0;
end
initial begin
    # 150 $finish;
end
initial begin
    $dumpfile("four_bit_RC.vcd");
    $dumpvars;
end
endmodule

Counters/four_bit_RC.vcd
$date
	Fri Aug 29 22:47:21 2025
$end
$version
	Icarus Verilog
$end
$timescale
	1s
$end
$scope module four_bit_RC_tb $end
$var wire 4 ! q [3:0] $end
$var reg 1 " clk $end
$var reg 1 # rst $end
$var reg 4 $ t [3:0] $end
$scope module DUT $end
$var wire 1 " clk $end
$var wire 1 # rst $end
$var wire 4 % t [3:0] $end
$var wire 4 & q [3:0] $end
$scope module M1 $end
$var wire 1 " clk $end
$var wire 1 ' in $end
$var wire 1 # rst $end
$var reg 1 ( out $end
$upscope $end
$scope module M2 $end
$var wire 1 ) clk $end
$var wire 1 * in $end
$var wire 1 # rst $end
$var reg 1 + out $end
$upscope $end
$scope module M3 $end
$var wire 1 , clk $end
$var wire 1 - in $end
$var wire 1 # rst $end
$var reg 1 . out $end
$upscope $end
$scope module M4 $end
$var wire 1 / clk $end
$var wire 1 0 in $end
$var wire 1 # rst $end
$var reg 1 1 out $end
$upscope $end
$upscope $end
$upscope $end
$enddefinitions $end
$comment Show the parameter values. $end
$dumpall
$end
#0
$dumpvars
01
10
0/
0.
1-
0,
0+
1*
0)
0(
1'
b0 &
b1111 %
b1111 $
1#
0"
b0 !
$end
#5
1"
#7
1)
0,
0/
1(
0+
0.
b1 !
b1 &
01
0#
#10
0"
#15
0)
b0 !
b0 &
0(
1"
#20
0"
#25
11
1/
1.
1,
1+
1)
b1111 !
b1111 &
1(
1"
#30
0"
#35
0)
b1110 !
b1110 &
0(
1"
#40
0"
#45
0,
0+
1)
b1101 !
b1101 &
1(
1"
#50
0"
#55
0)
b1100 !
b1100 &
0(
1"
#60
0"
#65
0/
0.
1,
1+
1)
b1011 !
b1011 &
1(
1"
#70
0"
#75
0)
b1010 !
b1010 &
0(
1"
#80
0"
#85
0,
0+
1)
b1001 !
b1001 &
1(
1"
#90
0"
#95
0)
b1000 !
b1000 &
0(
1"
#100
0"
#105
01
1/
1.
1,
1+
1)
b111 !
b111 &
1(
1"
#110
0"
#115
0)
b110 !
b110 &
0(
1"
#120
0"
#125
0,
0+
1)
b101 !
b101 &
1(
1"
#130
0"
#135
0)
b100 !
b100 &
0(
1"
#140
0"
#145
0/
0.
1,
1+
1)
b11 !
b11 &
1(
1"
