Counters/Syn_count.v
//Module design
module syn_c(clk,q);
input clk;
output reg [3:1] q;
wire [3:1] d;
reg [2:0] w;
initial q=3'b000;
always @(*) begin
    w[0]=q[3]|q[2];
    w[1]=~q[3]&~q[2];
    w[2]=q[3]&~q[1]; end
df A(w[0],clk,d[3]);
df B(w[1],clk,d[2]);
df C(w[2],clk,d[1]);
always @(posedge clk) 
q<=d; 
endmodule
module df(d,clk,q);
input d,clk;
output reg q;
always @(posedge clk)
q<=d;
endmodule
//Test bench
module tb;
reg clk;
wire [3:1] q;
syn_c DUT(clk,q);
initial clk=0;
always #5 clk=~clk;
initial begin
    $display("Time\tClock\tCount");
$monitor("%d\t%b\t%b",$time,clk,q);
#100 $finish;
end
initial begin 
    $dumpfile("Syn_count.vcd");
    $dumpvars(0,tb);
end
endmodule

Counters/Syn_count.vcd
$date
	Mon Jul 14 09:16:21 2025
$end
$version
	Icarus Verilog
$end
$timescale
	1s
$end
$scope module tb $end
$var wire 3 ! q [3:1] $end
$var reg 1 " clk $end
$scope module DUT $end
$var wire 1 " clk $end
$var wire 3 # d [3:1] $end
$var reg 3 $ q [3:1] $end
$var reg 3 % w [2:0] $end
$scope module A $end
$var wire 1 " clk $end
$var wire 1 & d $end
$var reg 1 ' q $end
$upscope $end
$scope module B $end
$var wire 1 " clk $end
$var wire 1 ( d $end
$var reg 1 ) q $end
$upscope $end
$scope module C $end
$var wire 1 " clk $end
$var wire 1 * d $end
$var reg 1 + q $end
$upscope $end
$upscope $end
$upscope $end
$enddefinitions $end
$comment Show the parameter values. $end
$dumpall
$end
#0
$dumpvars
x+
0*
x)
1(
x'
0&
b10 %
b0 $
bx #
0"
b0 !
$end
#5
x*
x(
x&
bx %
0'
1)
b10 #
0+
bx !
bx $
1"
#10
0"
#15
0*
0(
1&
b1 %
b10 !
b10 $
x+
x)
bx #
x'
1"
#20
0"
#25
x*
x(
x&
bx %
1'
0)
b100 #
0+
bx !
bx $
1"
#30
0"
#35
1*
0(
1&
b101 %
b100 !
b100 $
x+
x)
bx #
x'
1"
#40
0"
#45
x*
x(
x&
bx %
1'
0)
b101 #
1+
bx !
bx $
1"
#50
0"
#55
0*
0(
1&
b1 %
b101 !
b101 $
x+
x)
bx #
x'
1"
#60
0"
#65
x*
x(
x&
bx %
1'
0)
b100 #
0+
bx !
bx $
1"
#70
0"
#75
1*
0(
1&
b101 %
b100 !
b100 $
x+
x)
bx #
x'
1"
#80
0"
#85
x*
x(
x&
bx %
1'
0)
b101 #
1+
bx !
bx $
1"
#90
0"
#95
0*
0(
1&
b1 %
b101 !
b101 $
x+
x)
bx #
x'
1"
