FSM/FSM_syn_reset.v
//Module
module fsm(out,j,k,reset,clk);
input j,k,reset,clk;
output out;
parameter OFF=0, ON=1;
reg state, next_state;
//state transistion logic
always @(*) begin
case (state)
    OFF: next_state=j?ON:OFF;
    ON: next_state=k?OFF:ON;
    default: next_state<=OFF;
endcase
end
//State transistion
always @(posedge clk) begin
if (reset)
state<=OFF;
else
state<=next_state; 
end
//Output logic
assign out=(state==ON);
endmodule
//Test bench
`timescale 1ns/1ps
module fsm_tb;
reg J,K,res;
wire Q;
reg clk;
fsm DUT(.out(Q),.j(J),.k(K),.reset(res),.clk(clk));
initial clk=1'b0;
always #5 clk=~clk;
initial begin
    #3 res=1'b1;
    #3 res=1'b0;
    #7 J=1'b0;
    #10 J=1'b1;
    #10 K=1'b0;
    #10 K=1'b1;
    #10 res=1'b1;
    #3 $finish;
end
initial begin
    $dumpfile("fsm_syn_res.vcd");
    $dumpvars(0,fsm_tb);
end
initial begin
    $display("Time\tJ\tK\tQ");
    $monitor("%d\t%b\t%b\t%b\t%b",$time,clk,J,K,Q);
end
endmodule

FSM/fsm_syn_res.vcd
$date
	Tue Aug 19 19:19:52 2025
$end
$version
	Icarus Verilog
$end
$timescale
	1ps
$end
$scope module fsm_tb $end
$var wire 1 ! Q $end
$var reg 1 " J $end
$var reg 1 # K $end
$var reg 1 $ clk $end
$var reg 1 % res $end
$scope module DUT $end
$var wire 1 $ clk $end
$var wire 1 " j $end
$var wire 1 # k $end
$var wire 1 % reset $end
$var wire 1 ! out $end
$var parameter 32 & OFF $end
$var parameter 32 ' ON $end
$var reg 1 ( next_state $end
$var reg 1 ) state $end
$upscope $end
$upscope $end
$enddefinitions $end
$comment Show the parameter values. $end
$dumpall
b1 '
b0 &
$end
#0
$dumpvars
x)
x(
x%
0$
x#
x"
x!
$end
#3000
1%
#5000
0!
0)
1$
#6000
0%
#10000
0$
#13000
0(
0"
#15000
1$
#20000
0$
#23000
1(
1"
#25000
x(
1!
1)
1$
#30000
0$
#33000
1(
0#
#35000
1$
#40000
0$
#43000
0(
1#
#45000
1(
0!
0)
1$
#50000
0$
#53000
1%
