FSM/FSM_4_state.v
module fsm_4(in,out,clk);
input in,clk;
output out;
parameter A=2'b00, B=2'b01, C=2'b10, D=2'b11;
reg [1:0] state, next_state;
always @(*) begin
case (state)
A: next_state=in?B:A;
B: next_state=in?B:C;
C: next_state=in?D:A;
D: next_state=in?B:C;
default next_state=A;
endcase
end
always @(posedge clk) begin
state<=next_state;
end
assign out=(state==D);
endmodule
//Testbench
module tb;
reg in,clk;
wire out;
fsm_4 DUT(.in(in),.out(out),.clk(clk));
initial clk=0;
always #5 clk=~clk;
initial begin
    $display("Time\tClock\tinput\toutput");
    $monitor("%d\t%b\t%b\t%b",$time,clk,in,out);
    #3 in=1'b0;
    #10 in=1'b1;
    #10 in=1'b0;
    #10 in=1'b1;
    #10 in=1'b0;
    #30 $finish;
end
initial begin
    $dumpfile("FSM_4_state.vcd");
    $dumpvars;
end
endmodule

FSM/fsm_4.vcd
$date
	Thu Aug 21 19:25:59 2025
$end
$version
	Icarus Verilog
$end
$timescale
	1s
$end
$scope module tb $end
$var wire 1 ! out $end
$var reg 1 " clk $end
$var reg 1 # in $end
$scope module DUT $end
$var wire 1 " clk $end
$var wire 1 # in $end
$var wire 1 ! out $end
$var parameter 2 $ A $end
$var parameter 2 % B $end
$var parameter 2 & C $end
$var parameter 2 ' D $end
$var reg 2 ( next_state [1:0] $end
$var reg 2 ) state [1:0] $end
$upscope $end
$upscope $end
$enddefinitions $end
$comment Show the parameter values. $end
$dumpall
b11 '
b10 &
b1 %
b0 $
$end
#0
$dumpvars
bx )
bx (
x#
0"
x!
$end
#3
b0 (
0#
#5
0!
b0 )
1"
#10
0"
#13
b1 (
1#
#15
b1 )
1"
#20
0"
#23
b10 (
0#
#25
b0 (
b10 )
1"
#30
0"
#33
b11 (
1#
#35
b1 (
1!
b11 )
1"
#40
0"
#43
b10 (
0#
#45
b0 (
0!
b10 )
1"
#50
0"
#55
b0 )
1"
