FSM/water_level_controller.v
module wlc(dfr,fr1,fr2,fr3,clk,reset,s1,s2,s3);
input clk,reset,s1,s2,s3;
output reg dfr,fr1,fr2,fr3;
parameter q0=2'b00,q1=2'b01,q2=2'b10,q3=2'b11;
reg [1:0] state;
always @(posedge clk) begin
    if (reset) begin
        state<=q0;
        {fr1,fr2,fr3,dfr}<=4'b1111;
    end
    else begin
case(state)
q0: begin 
    if (s1) begin
    state<=q1;
    {fr1,fr2}<=2'b11;
    end
    else begin
        state<=q0;
        {fr1,fr2,fr3,dfr}<=4'b1111;
    end
end
q1: begin
    if (~s1&~s2&~s3) begin
    state<=q0;
    {fr1,fr2,fr3,dfr}<=4'b1111;
    end
     if (s1&s2) begin
    state<=q2;
    fr1<=1;
    end
end
q2: begin
    if (s1) begin
    state<=q1;
    {fr1,fr2,fr3,dfr}<=4'b1101;
    end
    if (s1&s2&s3) begin
    state<=q3;
    {fr1,fr2,fr3,dfr}<=4'b0000;
    end
end
q3: begin
    if (s1&s2) begin
    state<=q2;
    {fr1,fr2,fr3,dfr}<=4'b1001;
    end
    else begin
        state<=q3;
        {fr1,fr2,fr3,dfr}<=4'b0000;
    end
end
default:  begin
    state<=q0;
    {fr1,fr2,fr3,dfr}<=4'b1111;
end
endcase
end
end
endmodule
// Test bench
module wlc_tb;
reg reset,s1,s2,s3,clk;
wire fr1,fr2,fr3,dfr;
wlc DUT(dfr,fr1,fr2,fr3,clk,reset,s1,s2,s3);
initial clk=0;
always #5 clk=~clk;
initial begin
    $display("Time\tClock\tS1\tS2\tS3\tfr1\tfr2\tfr3\tdfr");
    $monitor("%d\t%b\t%b\t%b\t%b\t%b\t%b\t%b\t%b\t%b",$time,clk,reset,s1,s2,s3,fr1,fr2,fr3,dfr);
    $dumpfile("water_level_controller.vcd");
    $dumpvars;
    reset=1;
    s1=0;
    s2=0;
    s3=0;
    #7 reset=0;
    #10 s1=1; s2=0; s3=0;
    #10 s1=1; s2=1; s3=0;
    #10 s1=1; s2=1; s3=1;
    #10 s1=1; s2=1; s3=0;
    # 100 $finish;
end
endmodule

FSM/water_level_controller.vcd
$date
	Sat Aug 30 11:37:56 2025
$end
$version
	Icarus Verilog
$end
$timescale
	1s
$end
$scope module wlc_tb $end
$var wire 1 ! fr3 $end
$var wire 1 " fr2 $end
$var wire 1 # fr1 $end
$var wire 1 $ dfr $end
$var reg 1 % clk $end
$var reg 1 & reset $end
$var reg 1 ' s1 $end
$var reg 1 ( s2 $end
$var reg 1 ) s3 $end
$scope module DUT $end
$var wire 1 % clk $end
$var wire 1 & reset $end
$var wire 1 ' s1 $end
$var wire 1 ( s2 $end
$var wire 1 ) s3 $end
$var parameter 2 * q0 $end
$var parameter 2 + q1 $end
$var parameter 2 , q2 $end
$var parameter 2 - q3 $end
$var reg 1 $ dfr $end
$var reg 1 # fr1 $end
$var reg 1 " fr2 $end
$var reg 1 ! fr3 $end
$var reg 2 . state [1:0] $end
$upscope $end
$upscope $end
$enddefinitions $end
$comment Show the parameter values. $end
$dumpall
b11 -
b10 ,
b1 +
b0 *
$end
#0
$dumpvars
bx .
0)
0(
0'
1&
0%
x$
x#
x"
x!
$end
#5
1#
1"
1!
1$
b0 .
1%
#7
0&
#10
0%
#15
1%
#17
1'
#20
0%
#25
b1 .
1%
#27
1(
#30
0%
#35
b10 .
1%
#37
1)
#40
0%
#45
0#
0"
0$
0!
b11 .
1%
#47
0)
#50
0%
#55
1#
1$
b10 .
1%
#60
0%
#65
1"
b1 .
1%
#70
0%
#75
b10 .
1%
#80
0%
#85
b1 .
1%
#90
0%
#95
b10 .
1%
#100
0%
#105
b1 .
1%
#110
0%
#115
b10 .
1%
#120
0%
#125
b1 .
1%
#130
0%
#135
b10 .
1%
#140
0%
#145
b1 .
1%
